{"wires": [{"id": 0, "name": "yellow_wire", "color": "yellow", "state": "on_table", "coordinates": [[0.23242047876860378], [0.381136521339435], [0.0069254650333035635]]}, {"id": 1, "name": "black_wire", "color": "black", "state": "on_table", "coordinates": [[0.2734873371568182], [0.5342481083785934], [0.006921791939735774]]}, {"id": 2, "name": "blue_wire", "color": "blue", "state": "on_table", "coordinates": [[0.35828902928027234], [0.2886109907893096], [0.004240548451560772]]}, {"id": 3, "name": "orange_wire", "color": "orange", "state": "on_table", "coordinates": [[0.29662603688997397], [0.2694446753031314], [0.00471475848682767]]}, {"id": 4, "name": "white_wire", "color": "white", "state": "on_table", "coordinates": [[0.26790209085364897], [0.2830058069181121], [0.004631808273451546]]}, {"id": 5, "name": "black_wire", "color": "black", "state": "on_table", "coordinates": [[0.36091973065346206], [0.29569869405974436], [0.0035701412145618745]]}, {"id": 6, "name": "blue_wire", "color": "blue", "state": "on_table", "coordinates": [[0.28577797894637025], [0.4583620002913301], [0.006326851639021799]]}, {"id": 7, "name": "yellow_wire", "color": "yellow", "state": "on_table", "coordinates": [[0.41727938990552793], [0.2823554010981127], [0.005229999218986287]]}, {"id": 8, "name": "green_wire", "color": "green", "state": "on_table", "coordinates": [[0.16855493166842553], [0.38251546152719507], [0.00401423803061015]]}, {"id": 9, "name": "black_wire", "color": "black", "state": "on_table", "coordinates": [[0.39440049730985205], [0.17507586004616774], [0.006875354966113257]]}, {"id": 10, "name": "orange_wire", "color": "orange", "state": "on_table", "coordinates": [[0.36416357817170414], [0.13922945685020902], [0.006342043614766445]]}, {"id": 11, "name": "orange_wire", "color": "orange", "state": "on_table", "coordinates": [[0.34666506998390056], [0.23513788068359598], [0.0038999034332686047]]}, {"id": 12, "name": "yellow_wire", "color": "yellow", "state": "on_table", "coordinates": [[0.26085536714243535], [0.331158332879963], [0.0036872558756509527]]}, {"id": 13, "name": "red_wire", "color": "red", "state": "on_table", "coordinates": [[0.1996301835179059], [0.36094341102257277], [0.0041673711577679025]]}], "terminals": {"terminal_0": {"state": "empty", "coordinates": -0.027621084853182334}, "terminal_1": {"state": "empty", "coordinates": -0.027621082851237336}, "terminal_2": {"state": "empty", "coordinates": -0.02762108084929235}, "terminal_3": {"state": "empty", "coordinates": -0.027621078868890966}, "terminal_4": {"state": "empty", "coordinates": -0.027621076888489582}, "terminal_5": {"state": "empty", "coordinates": -0.027621074908088197}, "terminal_6": {"state": "empty", "coordinates": -0.027621072923613044}, "terminal_7": {"state": "empty", "coordinates": -0.027621070925647084}, "terminal_8": {"state": "empty", "coordinates": -0.027621068948675248}}}