{"wires": [{"id": 0, "name": "yellow_wire", "color": "yellow", "state": "on_table", "coordinates": [[0.25401396926772446], [0.17301170493831167], [0.006207965128740267]]}, {"id": 1, "name": "orange_wire", "color": "orange", "state": "on_table", "coordinates": [[0.32341354844965786], [0.3013727097594766], [0.00361451843524294]]}, {"id": 2, "name": "blue_wire", "color": "blue", "state": "on_table", "coordinates": [[0.33277185406191656], [0.2921225360733913], [0.006001499826079585]]}, {"id": 3, "name": "black_wire", "color": "black", "state": "on_table", "coordinates": [[0.2981066354080582], [0.37461458278628346], [0.005734882077502676]]}, {"id": 4, "name": "black_wire", "color": "black", "state": "on_table", "coordinates": [[0.20813467969089744], [0.2924469344941263], [0.005647555568799917]]}, {"id": 5, "name": "green_wire", "color": "green", "state": "on_table", "coordinates": [[0.3318266694353058], [0.4045292653955489], [0.0036989670278804844]]}, {"id": 6, "name": "green_wire", "color": "green", "state": "on_table", "coordinates": [[0.31614934486772206], [0.17357561401318528], [0.004715992821829894]]}, {"id": 7, "name": "white_wire", "color": "white", "state": "on_table", "coordinates": [[0.2404041738146118], [0.27643823660019445], [0.004143337516455108]]}, {"id": 8, "name": "red_wire", "color": "red", "state": "on_table", "coordinates": [[0.32865918464987864], [0.2269741551861983], [0.005946155362341169]]}], "terminals": {"terminal_0": {"state": "empty", "coordinates": -0.027621084853182334}, "terminal_1": {"state": "empty", "coordinates": -0.027621082851237336}, "terminal_2": {"state": "empty", "coordinates": -0.02762108084929235}, "terminal_3": {"state": "empty", "coordinates": -0.027621078868890966}, "terminal_4": {"state": "empty", "coordinates": -0.027621076888489582}, "terminal_5": {"state": "empty", "coordinates": -0.027621074908088197}, "terminal_6": {"state": "empty", "coordinates": -0.027621072923613044}, "terminal_7": {"state": "empty", "coordinates": -0.027621070925647084}, "terminal_8": {"state": "empty", "coordinates": -0.027621068948675248}}}